falcon_lambda/__init__.py
falcon_lambda/logger.py
falcon_lambda/warmer.py
falcon_lambda/wsgi.py
falcon_lambda/xray.py
falcon_lambda/utils/__init__.py
falcon_lambda/utils/aws.py
falcon_lambda/validators/__init__.py
falcon_lambda/validators/swagger.py
falcon_lambda-0.1.13.dist-info/DESCRIPTION.rst
falcon_lambda-0.1.13.dist-info/METADATA
falcon_lambda-0.1.13.dist-info/RECORD
falcon_lambda-0.1.13.dist-info/WHEEL
falcon_lambda-0.1.13.dist-info/entry_points.txt
falcon_lambda-0.1.13.dist-info/metadata.json
falcon_lambda-0.1.13.dist-info/top_level.txt
